omnicloud/dash/__init__.py
omnicloud/dash/_dash.py
omnicloud_dash-0.0.1.dist-info/LICENSE
omnicloud_dash-0.0.1.dist-info/METADATA
omnicloud_dash-0.0.1.dist-info/WHEEL
omnicloud_dash-0.0.1.dist-info/RECORD
