Metadata-Version: 2.1
Name: omnicloud-dash
Version: 0.0.1
Summary: Preconfigured Plotly Dash for Omnicloud
Home-page: https://omnicloud.world/apps
Keywords: omnicloud,supercloud,multicloud,cloud computing,migration,dash
Author: Iurii Tarasenko
Author-email: iurii@omnicloud.world
Requires-Python: >=3.10,<4.0
Classifier: Framework :: Dash
Classifier: Intended Audience :: Developers
Classifier: Intended Audience :: Information Technology
Classifier: License :: OSI Approved :: MIT License
Classifier: Operating System :: OS Independent
Classifier: Programming Language :: Python :: 3
Classifier: Programming Language :: Python :: 3.10
Classifier: Programming Language :: Python :: 3.11
Classifier: Programming Language :: Python :: 3.10
Classifier: Topic :: Software Development :: Libraries :: Python Modules
Requires-Dist: asgiref (>=3.6.0,<4.0.0)
Requires-Dist: dash-bootstrap-components (>=1.4.1,<2.0.0)
Requires-Dist: dash[compress] (>=2.9.2,<3.0.0)
Requires-Dist: hypercorn (>=0.14.3,<0.15.0)
Requires-Dist: jupyter-dash (>=0.4.2,<0.5.0)
Requires-Dist: python-dotenv (>=1.0.0,<2.0.0)
Project-URL: Documentation, https://docs.omnicloud.world/app-dash
Project-URL: Repository, https://github.com/omnicloudworld/app.dash
